AUTHORS
LICENSE
MANIFEST.in
README.rst
setup.py
cmsplugin_filer_html5video/__init__.py
cmsplugin_filer_html5video/cms_plugins.py
cmsplugin_filer_html5video/models.py
cmsplugin_filer_html5video/plugin_settings.py
cmsplugin_filer_html5video.egg-info/PKG-INFO
cmsplugin_filer_html5video.egg-info/SOURCES.txt
cmsplugin_filer_html5video.egg-info/dependency_links.txt
cmsplugin_filer_html5video.egg-info/not-zip-safe
cmsplugin_filer_html5video.egg-info/requires.txt
cmsplugin_filer_html5video.egg-info/top_level.txt
cmsplugin_filer_html5video/migrations/0001_initial.py
cmsplugin_filer_html5video/migrations/__init__.py
cmsplugin_filer_html5video/static/cmsplugin_filer_html5video/css/video-js.css
cmsplugin_filer_html5video/static/cmsplugin_filer_html5video/css/video-js.png
cmsplugin_filer_html5video/static/cmsplugin_filer_html5video/js/video.js
cmsplugin_filer_html5video/templates/cmsplugin_filer_html5video/video.html