Metadata-Version: 1.1
Name: cmsplugin-filer-html5video
Version: 0.1
Summary: HTML5 video plugin for django CMS and django-filer, using VideoJS
Home-page: https://github.com/piquadrat/cmsplugin-filer-html5video
Author: Benjamin Wohlwend
Author-email: piquadrat@gmail.com
License: BSD
Platform: UNKNOWN
Classifier: Development Status :: 4 - Beta
Classifier: Framework :: Django
Classifier: Intended Audience :: Developers
Classifier: License :: OSI Approved :: BSD License
Classifier: Operating System :: OS Independent
Classifier: Programming Language :: Python
Classifier: Topic :: Internet :: WWW/HTTP
